{
  "ark": "ark:/21198/z1j40b7h",
  "reconstruction": false,
  "type": {
    "id": "manuscript",
    "label": "Manuscript"
  },
  "shelfmark": "Sinai Syriac 130",
  "extent": "298 ff.",
  "weight": "1070.5 g",
  "dim": "174 x 152 x 86.0 mm",
  "state": {
    "id": "codex",
    "label": "Codex"
  },
  "part": [
    {
      "label": "Part 1",
      "support": [
        {
          "id": "paper",
          "label": "Paper"
        }
      ],
      "ot_layer": [
        {
          "id": "ark:/21198/s15s6f",
          "label": "Overtext Layer",
          "type": {
            "id": "overtext",
            "label": "Overtext"
          },
          "layer_record": {
            "ark": "ark:/21198/s15s6f",
            "reconstruction": false,
            "state": {
              "id": "overtext",
              "label": "Overtext"
            },
            "label": "Sinai Syriac 130, Overtext (Melkite)",
            "writing": [
              {
                "script": [
                  {
                    "id": "melkite",
                    "label": "Melkite",
                    "writing_system": "Syriac"
                  }
                ]
              }
            ],
            "text_unit": [
              {
                "id": "ark:/21198/s10d4b",
                "label": "Item 1",
                "locus": "ff. 1r-297v",
                "text_unit_record": {
                  "ark": "ark:/21198/s10d4b",
                  "reconstruction": false,
                  "label": "Horologion",
                  "locus": "ff. 1r-297v",
                  "lang": [
                    {
                      "id": "class1252",
                      "label": "Syriac"
                    }
                  ],
                  "work_wit": [
                    {
                      "work": {
                        "ark": "ark:/21198/s1dg6h",
                        "pref_title": "Horologion",
                        "genre": [
                          {
                            "id": "liturgical-texts",
                            "label": "Liturgical texts"
                          }
                        ]
                      },
                      "locus": "ff. 1r-297v",
                      "note": [
                        "A small portion toward the end switches to Arabic."
                      ]
                    }
                  ],
                  "parent": [
                    "ark:/21198/s15s6f"
                  ],
                  "desc_provenance": {
                    "rights": "Unless otherwise indicated, all metadata is copyright the authors and is released under the Creative Commons Attribution 4.0 International License (CC BY 4.0), https://creativecommons.org/licenses/by/4.0/."
                  }
                }
              }
            ],
            "parent": [
              "ark:/21198/z1j40b7h"
            ],
            "desc_provenance": {
              "rights": "Unless otherwise indicated, all metadata is copyright the authors and is released under the Creative Commons Attribution 4.0 International License (CC BY 4.0), https://creativecommons.org/licenses/by/4.0/."
            }
          }
        }
      ]
    }
  ],
  "para": [
    {
      "type": {
        "id": "history",
        "label": "History"
      },
      "locus": "f. 75r",
      "lang": [
        {
          "id": "arab1395",
          "label": "Arabic"
        }
      ],
      "as_written": "هذا المجموع المبارك ملك الولد الروحاني / القس موسى العاري / القاري[....] / نفعه الله وايانا بما فيه وكتبه الحقير مرقص خادم طور سينا",
      "translation": [
        "This blessed Anthology is owned by the spiritual son / […] priest Mūsá al-ʻĀrī / al-Qārī / May God make it useful to him and us. This was written by Marquṣ the servant of Mount Sinai"
      ]
    },
    {
      "type": {
        "id": "history",
        "label": "History"
      },
      "locus": "f. 274v",
      "lang": [
        {
          "id": "arab1395",
          "label": "Arabic"
        }
      ],
      "label": "Monastic assignment and endowment note",
      "as_written": "هذا الكتاب (الـ؟) برسم الولد الروحاني الراهب ميخاييل / ملك له يحدمن عليه واي موضع (؟) يسير عليه بالموت يكون وقف على / كنيسه للمكان الذي يتوفى فيه واي من اخرجه عنه بوجه من الوجوه يكون / تحت كلمه الله تعالى (الموت؟) سلطانها والويل ثم الويل لمن يرضى لنفسه / [....] / طور سينا [....] عفى الله عنه [....]",
      "note": [
        "Anonymous note assigning the manuscript to the monk Mīkhāʾīl; upon his death it is to become an endowment of the monastery at the place of his death, with a warning against removing it.",
        "Written vertically in pencil. The leaf is trimmed around"
      ]
    }
  ],
  "location": [
    {
      "id": "sinai-oc",
      "collection": "Old Collection",
      "repository": "St. Catherine's Monastery of the Sinai"
    }
  ],
  "bib": [
    {
      "id": "deb668b6-feec-4828-8749-a97441881226",
      "type": {
        "id": "ref",
        "label": "Reference"
      },
      "shortcode": "Kamil 1970",
      "citation": "Kāmil, Murād. Catalogue of All Manuscripts in the Monastery of St. Catherine on Mount Sinai. Harrassowitz, 1970",
      "range": "[110], p. 155"
    }
  ],
  "iiif": [
    {
      "type": {
        "id": "main",
        "label": "Main"
      },
      "manifest": "https://iiif.library.ucla.edu/ark%3A%2F21198%2Fz1j40b7h/manifest",
      "label": "Natural Light",
      "text_direction": "right-to-left",
      "behavior": "individuals",
      "thumbnail": "https://iiif.sinaimanuscripts.library.ucla.edu/iiif/2/ark%3A%2F21198%2Fz1j40b7h%2F8v60rg6m/full/!200,200/0/default.jpg"
    }
  ],
  "desc_provenance": {
    "rights": "Unless otherwise indicated, all metadata is copyright the authors and is released under the Creative Commons Attribution 4.0 International License (CC BY 4.0), https://creativecommons.org/licenses/by/4.0/."
  },
  "image_provenance": {
    "program": [
      {
        "label": "Sinai Library Digitization Project, Phase 1",
        "description": "Digitized under the Sinai Library Digitization Project, Phase 1 (2018-2023), a collaboration of St. Catherine’s Monastery of the Sinai, the Early Manuscripts Electronic Library, and UCLA Library, with funding from the Arcadia Fund, the Ahmanson Foundation, and the Steinmetz Family Foundation. The project provided high-resolution images and basic description of the Arabic and Syriac manuscripts held in the Monastery’s library.",
        "camera_operator": [
          "Vasilis Kasotakis"
        ],
        "imaging_date": "2019 September",
        "delivery": "6.1",
        "imaging_system": "BC100 - 2 cam., 740 ppi, 90mm lens"
      }
    ],
    "rights": "All manuscript images are the property of St. Catherine’s Monastery of the Sinai. No part of these images may be reproduced, reused, or distributed without prior written permission. For permissions and reuse requests, please contact sinai@library.ucla.edu."
  }
}