{
  "ark": "ark:/21198/s19s8f",
  "reconstruction": false,
  "label": "Varia",
  "locus": "ff. 1r-245r",
  "lang": [
    {
      "id": "arab1395",
      "label": "Arabic"
    }
  ],
  "work_wit": [
    {
      "work": {
        "desc_title": "Portions of a life",
        "genre": [
          {
            "id": "hagiographies",
            "label": "Hagiographies"
          }
        ]
      },
      "locus": "f. 1r-v"
    },
    {
      "work": {
        "desc_title": "Life and Miracles of St. Simeon the Stylite",
        "genre": [
          {
            "id": "hagiographies",
            "label": "Hagiographies"
          }
        ]
      },
      "locus": "ff. 2r-142r"
    },
    {
      "work": {
        "desc_title": "Menologion for the month of Haziran (June)",
        "genre": [
          {
            "id": "liturgical-texts",
            "label": "Liturgical texts"
          },
          {
            "id": "lectionaries",
            "label": "Lectionaries"
          },
          {
            "id": "biblical-texts",
            "label": "Biblical texts"
          }
        ]
      },
      "locus": "ff. 143r-245r",
      "contents": [
        {
          "label": "Life of Onuphrius, ff. 156v-169r"
        },
        {
          "label": "Life of Elisha the prophet, ff. 170r-183v"
        },
        {
          "label": "Life of Leontius, ff. 183v-190r"
        },
        {
          "label": "Gospel of Judah, brother of the Lord, ff. 190v-201v"
        },
        {
          "label": "Encomium and Mimar of John Chrysostom on the birth of John the Baptist, ff. 201v-205v"
        },
        {
          "label": "Encomium of Jacob of Serugh on John the Baptist, ff. 205v-211v"
        },
        {
          "label": "Life of Phebronia, ff. 212av"
        },
        {
          "label": "Account of Peter and Paul, ff. 232r-242v"
        },
        {
          "label": "Life and Miracles of Peter the Apostle, ff. 243r-245r"
        }
      ]
    }
  ],
  "desc_provenance": {
    "rights": "Unless otherwise indicated, all metadata is copyright the authors and is released under the Creative Commons Attribution 4.0 International License (CC BY 4.0), https://creativecommons.org/licenses/by/4.0/."
  },
  "cataloguer": [
    {
      "message": "Texts identified and described as part of the NEH Sinai Data Portal project (2021-2024).",
      "contributor": [
        "Justin Arnwine"
      ],
      "added_by": "sinai-admin",
      "timestamp": "2025-12-08T15:02+00:00"
    }
  ],
  "parent": [
    "ark:/21198/s1h90f"
  ]
}