{
  "ark_ssi": "ark:/21198/z1j20v6k",
  "ms_type_ssi": "Undertext Object",
  "state_ssi": "Undertext Object",
  "features_ssim": [],
  "support_ssim": [
    "Parchment"
  ],
  "repository_ssim": [
    "St. Catherine's Monastery of the Sinai"
  ],
  "collection_ssim": [
    "Old Collection"
  ],
  "names_ssim": [],
  "places_ssim": [],
  "date_types_ssim": [],
  "program_ssim": [
    "Sinai Palimpsests Project"
  ],
  "reconstructed_from_ssim": [
    "ark:/21198/z1v9962j"
  ],
  "reconstructed_from_shelfmark_ssim": [
    "Sinai Greek 930"
  ],
  "ot_script_ssim": [
    "Kufic"
  ],
  "ot_writing_system_ssim": [
    "Arabic"
  ],
  "ot_genre_ssim": [
    "Biblical texts"
  ],
  "ot_year_isim": [],
  "ot_language_ssim": [
    "Arabic"
  ],
  "ot_works_ssim": [],
  "para_script_ssim": [],
  "para_writing_system_ssim": [],
  "para_year_isim": [],
  "para_language_ssim": [],
  "para_works_ssim": [],
  "para_genre_ssim": [],
  "para_names_ssim": [],
  "para_type_ssim": [],
  "uto_script_ssim": [],
  "uto_language_ssim": [],
  "uto_year_isim": [],
  "shelfmark_ssi": "UTO Sinai Greek 930, SPP No. 211",
  "titles_tesim": [
    "Exodus",
    "Judeo-Arabic translation of Exodus"
  ],
  "names_tesim": [],
  "exerpts_tesim": [],
  "places_tesim": [],
  "contents_tesim": [
    "Exodus",
    "Judeo-Arabic translation of Exodus",
    "This is a Judeo-Arabic, probably Karaite translation of North African origin, in Arabic script. The translation was clearly made from a Hebrew original. The text uses the \"Maghrebine\" form of 1 sg. imperfect (with the n- prefix): e.g., fols. 7v and 12r; the letter /f/ sometimes has a dot underneath. The translation is different from both Saadia and Yefet"
  ],
  "paracontent_tesim": [],
  "full_text_tesim": [
    "Arabic",
    "Exodus",
    "Judeo-Arabic translation of Exodus",
    "Kufic",
    "Late kufi",
    "Parchment",
    "The Arabic undertext runs at a right angle to the overtext",
    "The full number of lines is not always preserved",
    "This is a Judeo-Arabic, probably Karaite translation of North African origin, in Arabic script. The translation was clearly made from a Hebrew original. The text uses the \"Maghrebine\" form of 1 sg. imperfect (with the n- prefix): e.g., fols. 7v and 12r; the letter /f/ sometimes has a dot underneath. The translation is different from both Saadia and Yefet",
    "UTO Sinai Greek 930, SPP No. 211",
    "ark:/21198/z1j20v6k",
    "spputos"
  ],
  "cataloguer_tesim": [
    "Alexander Treiger"
  ],
  "last_modified_dtsi": "2025-12-15T22:33:00Z",
  "manuscript_json_ts": "{\"ark\":\"ark:/21198/z1j20v6k\",\"reconstruction\":true,\"type\":{\"id\":\"uto\",\"label\":\"Undertext Object\"},\"shelfmark\":\"UTO Sinai Greek 930, SPP No. 211\",\"extent\":\"16 fols.\",\"weight\":\"Original field name: Format.weight\",\"dim\":\"Original field name: Format.dimensions\",\"state\":{\"id\":\"uto\",\"label\":\"Undertext Object\"},\"fol\":\"Reconstructed folio order, ff. 56v (1:1-?), 4r (2:9-13), 3v (2:14-17), 4v (2:18-23), 3r (2:24-3:4), 22v (4:5-7), 12r (5:23 - 6:3), 7v (6:4-?), 112r (9:28-33), 101v (10:19-?), 102r (10:?-28), 26v (11:9 - 12:4), 23v (12:15-19), 5v (12:40-47), 2r (12:48 - 13:4), 5r (13:5-10), 2v (13:11-15), 66v (13:16-19)\",\"part\":[{\"label\":\"Part 1\",\"support\":[{\"id\":\"parchment\",\"label\":\"Parchment\"}],\"ot_layer\":[{\"id\":\"ark:/21198/s1zw6m\",\"label\":\"Overtext Layer\",\"type\":{\"id\":\"overtext\",\"label\":\"Overtext\"},\"layer_record\":{\"ark\":\"ark:/21198/s1zw6m\",\"reconstruction\":false,\"state\":{\"id\":\"undertext\",\"label\":\"Undertext\"},\"label\":\"Sinai Greek 930, Undertext (Kufic)\",\"locus\":\"ff. 2–5, 7v, 12r, 22v, 23v, 26v, 27v, 56v, 66v, 73r, 101v, 102r, 112r\",\"writing\":[{\"script\":[{\"id\":\"kufic\",\"label\":\"Kufic\",\"writing_system\":\"Arabic\"}],\"note\":[\"Late kufi\"]}],\"layout\":[{\"columns\":\"1 columns\",\"lines\":\"16 lines\",\"note\":[\"The full number of lines is not always preserved\",\"The Arabic undertext runs at a right angle to the overtext\"]}],\"text_unit\":[{\"id\":\"ark:/21198/s1mx2b\",\"label\":\"Item 1\",\"text_unit_record\":{\"ark\":\"ark:/21198/s1mx2b\",\"reconstruction\":false,\"label\":\"Judeo-Arabic translation of Exodus\",\"lang\":[{\"id\":\"arab1395\",\"label\":\"Arabic\"}],\"work_wit\":[{\"work\":{\"desc_title\":\"Exodus\",\"genre\":[{\"id\":\"biblical-texts\",\"label\":\"Biblical texts\"}]},\"alt_title\":\"Judeo-Arabic translation of Exodus\",\"note\":[\"This is a Judeo-Arabic, probably Karaite translation of North African origin, in Arabic script. The translation was clearly made from a Hebrew original. The text uses the \\\"Maghrebine\\\" form of 1 sg. imperfect (with the n- prefix): e.g., fols. 7v and 12r; the letter /f/ sometimes has a dot underneath. The translation is different from both Saadia and Yefet\"]}],\"cataloguer\":[{\"message\":\"Description and identification of undertexts as part of SPP (2011-2016). Migrated to SMDL in 2025.\",\"contributor\":[\"Alexander Treiger\"],\"added_by\":\"sinai-admin\",\"timestamp\":\"2025-12-15T22:33:00Z\"}],\"parent\":[\"ark:/21198/s1zw6m\"],\"desc_provenance\":{\"program\":[{\"label\":\"Sinai Palimpsests Project\",\"description\":\"Imaged and studied as part of the Sinai Palimpsests Project (2011–2016), a collaboration between St. Catherine’s Monastery of the Sinai, the Early Manuscripts Electronic Library, and UCLA Library, funded by the Arcadia Fund and the Ahmanson Foundation. The project used multispectral imaging and scholarly analysis to recover and document erased and obscured texts in palimpsest manuscripts from the monastery’s collection.\"}],\"rights\":\"Unless otherwise indicated, all metadata is copyright the authors and is released under the Creative Commons Attribution 4.0 International License (CC BY 4.0), https://creativecommons.org/licenses/by/4.0/.\"}}}],\"cataloguer\":[{\"message\":\"Description and identification of undertexts as part of SPP (2011-2016). Migrated to SMDL in 2025.\",\"contributor\":[\"Alexander Treiger\"],\"added_by\":\"sinai-admin\",\"timestamp\":\"2025-12-15T22:33:00Z\"}],\"parent\":[\"ark:/21198/z1v9962j\",\"ark:/21198/z1j20v6k\"],\"desc_provenance\":{\"program\":[{\"label\":\"Sinai Palimpsests Project\",\"description\":\"Imaged and studied as part of the Sinai Palimpsests Project (2011–2016), a collaboration between St. Catherine’s Monastery of the Sinai, the Early Manuscripts Electronic Library, and UCLA Library, funded by the Arcadia Fund and the Ahmanson Foundation. The project used multispectral imaging and scholarly analysis to recover and document erased and obscured texts in palimpsest manuscripts from the monastery’s collection.\"}],\"rights\":\"Unless otherwise indicated, all metadata is copyright the authors and is released under the Creative Commons Attribution 4.0 International License (CC BY 4.0), https://creativecommons.org/licenses/by/4.0/.\"}}}]}],\"location\":[{\"id\":\"sinai-oc\",\"collection\":\"Old Collection\",\"repository\":\"St. Catherine's Monastery of the Sinai\"}],\"iiif\":[{\"type\":{\"id\":\"main\",\"label\":\"Main\"},\"manifest\":\"https://sinai-images.library.ucla.edu/iiif/ark:%2F21198%2Fz1v9962j/manifest\",\"label\":\"SPP\",\"thumbnail\":\"https://sinai-images.library.ucla.edu/iiif/ark:%2F21198%2Fz1ng5m90/0,902,5412,5412/150,150/0/default.jpg\"}],\"cataloguer\":[{\"message\":\"Description and identification of undertexts as part of SPP (2011-2016). Migrated to SMDL in 2025.\",\"contributor\":[\"Alexander Treiger\"],\"added_by\":\"sinai-admin\",\"timestamp\":\"2025-12-15T22:33:00Z\"}],\"reconstructed_from\":[{\"id\":\"ark:/21198/z1v9962j\",\"shelfmark\":\"Sinai Greek 930\"}],\"desc_provenance\":{\"rights\":\"Unless otherwise indicated, all metadata is copyright the authors and is released under the Creative Commons Attribution 4.0 International License (CC BY 4.0), https://creativecommons.org/licenses/by/4.0/.\"},\"image_provenance\":{\"program\":[{\"label\":\"Sinai Palimpsests Project\",\"description\":\"Imaged and studied as part of the Sinai Palimpsests Project (2011–2016), a collaboration between St. Catherine’s Monastery of the Sinai, the Early Manuscripts Electronic Library, and UCLA Library, funded by the Arcadia Fund and the Ahmanson Foundation. The project used multispectral imaging and scholarly analysis to recover and document erased and obscured texts in palimpsest manuscripts from the monastery’s collection.\",\"delivery\":\"spputos\"}],\"rights\":\"All manuscript images are the property of St. Catherine’s Monastery of the Sinai. No part of these images may be reproduced, reused, or distributed without prior written permission. For permissions and reuse requests, please contact sinai@library.ucla.edu.\"}}",
  "id": "ark:/21198/z1j20v6k",
  "has_model_ssim": [
    "Work"
  ],
  "visibility_ssi": "open",
  "discover_access_group_ssim": [
    "public"
  ],
  "read_access_group_ssim": [
    "public"
  ],
  "download_access_person_ssim": [
    "public"
  ],
  "thumbnail_url_ss": "https://sinai-images.library.ucla.edu/iiif/ark:%2F21198%2Fz1ng5m90/0,902,5412,5412/150,150/0/default.jpg",
  "iiif_manifest_url_ssi": "https://sinai-images.library.ucla.edu/iiif/ark:%2F21198%2Fz1v9962j/manifest",
  "header_index_tesim": [
    "UTO Sinai Greek 930, SPP No. 211",
    "16 fols."
  ],
  "ot_date_tesim": [],
  "para_date_tesim": [],
  "uto_date_tesim": [],
  "extent_tesi": "16 fols.",
  "text_unit_labels_tesim": [
    "Judeo-Arabic translation of Exodus"
  ],
  "origin_date_values_tesim": []
}